robotframeworklexer.py
robotframeworklexer-1.1.dist-info/LICENSE.txt
robotframeworklexer-1.1.dist-info/METADATA
robotframeworklexer-1.1.dist-info/WHEEL
robotframeworklexer-1.1.dist-info/entry_points.txt
robotframeworklexer-1.1.dist-info/top_level.txt
robotframeworklexer-1.1.dist-info/RECORD
