Metadata-Version: 1.1
Name: robotframeworklexer
Version: 1.1
Summary: Pygments lexer for Robot Framework test data.
Home-page: https://github.com/robotframework/pygmentslexer
Author: Pekka Klärck
Author-email: peke@iki.fi
License: Apache License 2.0
Download-URL: https://pypi.org/project/robotframeworklexer
Keywords: pygments robotframework
Platform: any
Requires: pygments
